serverless_tools/__init__.py
serverless_tools-0.0.1.dist-info/LICENSE.md
serverless_tools-0.0.1.dist-info/METADATA
serverless_tools-0.0.1.dist-info/WHEEL
serverless_tools-0.0.1.dist-info/top_level.txt
serverless_tools-0.0.1.dist-info/RECORD
